tk3u8/__init__.py
tk3u8/__main__.py
tk3u8/_version.py
tk3u8/constants.py
tk3u8/exceptions.py
tk3u8/messages.py
tk3u8/options_handler.py
tk3u8/paths_handler.py
tk3u8/cli/__init__.py
tk3u8/cli/__main__.py
tk3u8/cli/args_handler.py
tk3u8/cli/console.py
tk3u8/cli/logging.py
tk3u8/cli/main.py
tk3u8/cli/utils.py
tk3u8/core/__init__.py
tk3u8/core/downloader.py
tk3u8/core/extractor.py
tk3u8/core/helper.py
tk3u8/core/model.py
tk3u8/core/stream_metadata_handler.py
tk3u8/session/__init__.py
tk3u8/session/request_handler.py
tk3u8-0.4.0.dist-info/licenses/LICENSE
tk3u8-0.4.0.dist-info/METADATA
tk3u8-0.4.0.dist-info/WHEEL
tk3u8-0.4.0.dist-info/entry_points.txt
tk3u8-0.4.0.dist-info/top_level.txt
tk3u8-0.4.0.dist-info/RECORD
