Metadata-Version: 2.4
Name: tk3u8
Version: 0.4.0
Summary: A TikTok live downloader, written in Python.
Author-email: Scoofszlo <scoofszlo@gmail.com>
Project-URL: Source, https://github.com/Scoofszlo/tk3u8
Project-URL: Documentation, https://github.com/Scoofszlo/tk3u8/wiki
Project-URL: Issues, https://github.com/Scoofszlo/tk3u8/issues
Project-URL: Changelog, https://github.com/Scoofszlo/tk3u8/releases
Keywords: live,recording,tiktok,tiktok-downloader,tiktok-live,tiktok-tool,tiktok-live-downloader,tiktok-recorder,tiktok-live-stream
Classifier: Programming Language :: Python :: 3
Classifier: Programming Language :: Python :: 3.10
Classifier: Operating System :: OS Independent
Classifier: Development Status :: 4 - Beta
Classifier: Intended Audience :: End Users/Desktop
Classifier: Topic :: Internet
Classifier: Topic :: Multimedia
Classifier: Topic :: Utilities
Classifier: Topic :: Multimedia :: Video
Classifier: Topic :: Multimedia :: Video :: Capture
Requires-Python: >=3.10
License-File: LICENSE
Requires-Dist: bs4==0.0.2
Requires-Dist: platformdirs==4.3.8
Requires-Dist: requests==2.32.4
Requires-Dist: rich==14.0.0
Requires-Dist: rich-argparse==1.7.1
Requires-Dist: toml==0.10.2
Requires-Dist: yt-dlp==2025.6.25
Dynamic: license-file
